odoo/addons/base_time_dependent_parameter/README.rst
odoo/addons/base_time_dependent_parameter/__init__.py
odoo/addons/base_time_dependent_parameter/__manifest__.py
odoo/addons/base_time_dependent_parameter/i18n/base_time_dependent_parameter.pot
odoo/addons/base_time_dependent_parameter/models/__init__.py
odoo/addons/base_time_dependent_parameter/models/base.py
odoo/addons/base_time_dependent_parameter/models/base_time_parameter.py
odoo/addons/base_time_dependent_parameter/models/base_time_parameter_value.py
odoo/addons/base_time_dependent_parameter/readme/CONTRIBUTORS.rst
odoo/addons/base_time_dependent_parameter/readme/DESCRIPTION.rst
odoo/addons/base_time_dependent_parameter/readme/USAGE.rst
odoo/addons/base_time_dependent_parameter/security/ir.model.access.csv
odoo/addons/base_time_dependent_parameter/security/security.xml
odoo/addons/base_time_dependent_parameter/static/icon.png
odoo/addons/base_time_dependent_parameter/static/description/icon.png
odoo/addons/base_time_dependent_parameter/static/description/index.html
odoo/addons/base_time_dependent_parameter/views/base_time_parameter_views.xml
odoo14_addon_base_time_dependent_parameter-14.0.1.0.1.dist-info/METADATA
odoo14_addon_base_time_dependent_parameter-14.0.1.0.1.dist-info/WHEEL
odoo14_addon_base_time_dependent_parameter-14.0.1.0.1.dist-info/top_level.txt
odoo14_addon_base_time_dependent_parameter-14.0.1.0.1.dist-info/RECORD
